{"version":1,"resource":"vscode-userdata:/User/settings.json","entries":[{"id":"fXbX.json","timestamp":1735980094084},{"id":"go76.json","timestamp":1735980094099},{"id":"0vrk.json","timestamp":1735980094112},{"id":"us7x.json","timestamp":1735980094122},{"id":"Rzyh.json","timestamp":1735980101519},{"id":"hTPb.json","timestamp":1737920543971},{"id":"2Tza.json","timestamp":1737920543995},{"id":"tnj3.json","timestamp":1737920544015},{"id":"rPp7.json","timestamp":1737920544033},{"id":"yEaB.json","timestamp":1737920552623}]}